obafgkm/__init__.py
obafgkm/main.py
obafgkm/plot.py
obafgkm/prompt.py
obafgkm/rcparams.txt
obafgkm/star_types.csv
obafgkm/docs/conf.py
obafgkm/normalized_spectra/teff_3000.0_logg_0.0_mh_-2.0.txt
obafgkm/normalized_spectra/teff_3000.0_logg_0.0_mh_0.0.txt
obafgkm/normalized_spectra/teff_3000.0_logg_0.0_mh_0.5.txt
obafgkm/normalized_spectra/teff_3000.0_logg_1.0_mh_-2.0.txt
obafgkm/normalized_spectra/teff_3000.0_logg_1.0_mh_0.0.txt
obafgkm/normalized_spectra/teff_3000.0_logg_1.0_mh_0.5.txt
obafgkm/normalized_spectra/teff_3000.0_logg_2.0_mh_-2.0.txt
obafgkm/normalized_spectra/teff_3000.0_logg_2.0_mh_0.0.txt
obafgkm/normalized_spectra/teff_3000.0_logg_2.0_mh_0.5.txt
obafgkm/normalized_spectra/teff_3000.0_logg_3.0_mh_-2.0.txt
obafgkm/normalized_spectra/teff_3000.0_logg_3.0_mh_0.0.txt
obafgkm/normalized_spectra/teff_3000.0_logg_3.0_mh_0.5.txt
obafgkm/normalized_spectra/teff_3000.0_logg_4.0_mh_-2.0.txt
obafgkm/normalized_spectra/teff_3000.0_logg_4.0_mh_0.0.txt
obafgkm/normalized_spectra/teff_3000.0_logg_4.0_mh_0.5.txt
obafgkm/normalized_spectra/teff_3000.0_logg_5.0_mh_-2.0.txt
obafgkm/normalized_spectra/teff_3000.0_logg_5.0_mh_0.0.txt
obafgkm/normalized_spectra/teff_3000.0_logg_5.0_mh_0.5.txt
obafgkm/normalized_spectra/teff_4000.0_logg_0.0_mh_-2.0.txt
obafgkm/normalized_spectra/teff_4000.0_logg_0.0_mh_0.0.txt
obafgkm/normalized_spectra/teff_4000.0_logg_0.0_mh_0.5.txt
obafgkm/normalized_spectra/teff_4000.0_logg_1.0_mh_-2.0.txt
obafgkm/normalized_spectra/teff_4000.0_logg_1.0_mh_0.0.txt
obafgkm/normalized_spectra/teff_4000.0_logg_1.0_mh_0.5.txt
obafgkm/normalized_spectra/teff_4000.0_logg_2.0_mh_-2.0.txt
obafgkm/normalized_spectra/teff_4000.0_logg_2.0_mh_0.0.txt
obafgkm/normalized_spectra/teff_4000.0_logg_2.0_mh_0.5.txt
obafgkm/normalized_spectra/teff_4000.0_logg_3.0_mh_-2.0.txt
obafgkm/normalized_spectra/teff_4000.0_logg_3.0_mh_0.0.txt
obafgkm/normalized_spectra/teff_4000.0_logg_3.0_mh_0.5.txt
obafgkm/normalized_spectra/teff_4000.0_logg_4.0_mh_-2.0.txt
obafgkm-0.1.4.dist-info/licenses/LICENSE
obafgkm-0.1.4.dist-info/METADATA
obafgkm-0.1.4.dist-info/WHEEL
obafgkm-0.1.4.dist-info/top_level.txt
obafgkm-0.1.4.dist-info/RECORD
