Metadata-Version: 2.4
Name: obafgkm
Version: 0.1.4
License-File: LICENSE
Requires-Dist: numpy
Requires-Dist: pandas
Requires-Dist: astropy
Requires-Dist: matplotlib
Requires-Dist: pytest
Requires-Dist: pyqt5
Requires-Dist: sphinx-rtd-theme==3.0.2
Dynamic: license-file
